pyasoc/__init__.py
pyasoc/api/__init__.py
pyasoc/api/account_api.py
pyasoc/api/apps_api.py
pyasoc/api/asset_groups_api.py
pyasoc/api/business_units_api.py
pyasoc/api/domains_api.py
pyasoc/api/file_upload_api.py
pyasoc/api/fix_groups_api.py
pyasoc/api/issues_api.py
pyasoc/api/os_libraries_api.py
pyasoc/api/policies_api.py
pyasoc/api/presences_api.py
pyasoc/api/reports_api.py
pyasoc/api/roles_api.py
pyasoc/api/scans_api.py
pyasoc/api/tools_api.py
pyasoc/api/users_api.py
pyasoc/api/webhooks_api.py
pyasoc/api_client.py
pyasoc/asoc.py
pyasoc/cli.py
pyasoc/configuration.py
pyasoc/models/__init__.py
pyasoc/models/app_scan_saa_s_controllers_scans_controller_data.py
pyasoc/models/app_scan_saa_s_controllers_scans_controller_is_valid_url_response.py
pyasoc/models/app_scan_saa_s_models_v2_business_unit_model.py
pyasoc/models/app_scan_saa_s_models_v2_change.py
pyasoc/models/app_scan_saa_s_models_v2_dynamic_analyzer_scan.py
pyasoc/models/app_scan_saa_s_models_v2_dynamic_analyzer_scan_execution.py
pyasoc/models/app_scan_saa_s_models_v2_error_response.py
pyasoc/models/app_scan_saa_s_models_v2_explore_data_counters_model.py
pyasoc/models/app_scan_saa_s_models_v2_iast_analyzer.py
pyasoc/models/app_scan_saa_s_models_v2_iast_analyzer_scan_execution.py
pyasoc/models/app_scan_saa_s_models_v2_issue_change_set.py
pyasoc/models/app_scan_saa_s_models_v2_license_library_model.py
pyasoc/models/app_scan_saa_s_models_v2_min_presence_data.py
pyasoc/models/app_scan_saa_s_models_v2_min_scan_data.py
pyasoc/models/app_scan_saa_s_models_v2_min_scan_execution.py
pyasoc/models/app_scan_saa_s_models_v2_new_business_unit_model.py
pyasoc/models/app_scan_saa_s_models_v2_new_webhook.py
pyasoc/models/app_scan_saa_s_models_v2_sca_analyzer_scan.py
pyasoc/models/app_scan_saa_s_models_v2_sca_analyzer_scan_execution.py
pyasoc/models/app_scan_saa_s_models_v2_scan.py
pyasoc/models/app_scan_saa_s_models_v2_scan1.py
pyasoc/models/app_scan_saa_s_models_v2_scan_execution.py
py_asoc-0.3.1.dist-info/LICENSE
py_asoc-0.3.1.dist-info/METADATA
py_asoc-0.3.1.dist-info/WHEEL
py_asoc-0.3.1.dist-info/entry_points.txt
py_asoc-0.3.1.dist-info/RECORD
