Metadata-Version: 2.1
Name: py-asoc
Version: 0.3.1
Summary: Description
Home-page: https://github.com/mumblepins/py-asoc/
License: MIT
Author: Daniel Sullivan
Author-email: daniel.j.sullivan@state.mn.us
Requires-Python: >=3.8,<4.0
Classifier: License :: OSI Approved :: MIT License
Classifier: Programming Language :: Python :: 3
Classifier: Programming Language :: Python :: 3.8
Classifier: Programming Language :: Python :: 3.9
Classifier: Programming Language :: Python :: 3.10
Classifier: Programming Language :: Python :: 3.11
Provides-Extra: badges
Requires-Dist: certifi
Requires-Dist: click (>=8.1.3,<9.0.0)
Requires-Dist: cloup
Requires-Dist: javascript ; extra == "badges"
Requires-Dist: python-dateutil
Requires-Dist: pytz
Requires-Dist: urllib3
Project-URL: Documentation, https://mumblepins.github.io/py-asoc/
Project-URL: Repository, https://github.com/mumblepins/py-asoc/
